{
  "project_info": {
    "project_number": "332756337468",
    "project_id": "friendy-e59a4",
    "storage_bucket": "friendy-e59a4.appspot.com"
  },
  "client": [
    {
      "client_info": {
        "mobilesdk_app_id": "1:332756337468:android:eb2b098ffdc0e59d4a1439",
        "android_client_info": {
          "package_name": "com.example.friendy"
        }
      },
      "oauth_client": [
        {
          "client_id": "332756337468-htd08jngnton4bp6qf6nfdh6ks9r77mg.apps.googleusercontent.com",
          "client_type": 3
        }
      ],
      "api_key": [
        {
          "current_key": "AIzaSyANFDRsV1nYeU4XS1_IFGFAajLca_OQ4Yk"
        }
      ],
      "services": {
        "appinvite_service": {
          "other_platform_oauth_client": [
            {
              "client_id": "332756337468-htd08jngnton4bp6qf6nfdh6ks9r77mg.apps.googleusercontent.com",
              "client_type": 3
            }
          ]
        }
      }
    }
  ],
  "configuration_version": "1"
}